huaweicloudsdkmetastudio/__init__.py
huaweicloudsdkmetastudio/v1/__init__.py
huaweicloudsdkmetastudio/v1/metastudio_async_client.py
huaweicloudsdkmetastudio/v1/metastudio_client.py
huaweicloudsdkmetastudio/v1/model/__init__.py
huaweicloudsdkmetastudio/v1/model/access_type_enum.py
huaweicloudsdkmetastudio/v1/model/action_basic_sample_info.py
huaweicloudsdkmetastudio/v1/model/action_config.py
huaweicloudsdkmetastudio/v1/model/action_mark_item.py
huaweicloudsdkmetastudio/v1/model/action_sample_info.py
huaweicloudsdkmetastudio/v1/model/action_tag_info.py
huaweicloudsdkmetastudio/v1/model/active_code_info.py
huaweicloudsdkmetastudio/v1/model/allocate_sp_resource_info.py
huaweicloudsdkmetastudio/v1/model/allocate_sp_resource_summary_info.py
huaweicloudsdkmetastudio/v1/model/asr_type_enum.py
huaweicloudsdkmetastudio/v1/model/assess_property.py
huaweicloudsdkmetastudio/v1/model/assess_result.py
huaweicloudsdkmetastudio/v1/model/asset_action_result.py
huaweicloudsdkmetastudio/v1/model/asset_extra_meta.py
huaweicloudsdkmetastudio/v1/model/asset_file_info.py
huaweicloudsdkmetastudio/v1/model/asset_shared_config.py
huaweicloudsdkmetastudio/v1/model/attachment_uploading_address.py
huaweicloudsdkmetastudio/v1/model/audio_asset_meta.py
huaweicloudsdkmetastudio/v1/model/audio_drive_action_config.py
huaweicloudsdkmetastudio/v1/model/audio_info.py
huaweicloudsdkmetastudio/v1/model/audit_result_admin_audit_result.py
huaweicloudsdkmetastudio/v1/model/audit_result_system_audit_result.py
huaweicloudsdkmetastudio/v1/model/audit_result_system_audit_result_errors.py
huaweicloudsdkmetastudio/v1/model/audition_file.py
huaweicloudsdkmetastudio/v1/model/auto_operation_config.py
huaweicloudsdkmetastudio/v1/model/background_config_info.py
huaweicloudsdkmetastudio/v1/model/background_image_config.py
huaweicloudsdkmetastudio/v1/model/background_music_config.py
huaweicloudsdkmetastudio/v1/model/batch_asset_action_req.py
huaweicloudsdkmetastudio/v1/model/batch_confirm_live_commands_req.py
huaweicloudsdkmetastudio-3.1.184.dist-info/METADATA
huaweicloudsdkmetastudio-3.1.184.dist-info/WHEEL
huaweicloudsdkmetastudio-3.1.184.dist-info/licenses/LICENSE
huaweicloudsdkmetastudio-3.1.184.dist-info/RECORD
